xcbm/MGCDB84.py
xcbm/Input_Scripts/calc.py
xcbm/MGCDB84_Dataset/ex.py
xcbm-0.1.2.dist-info/licenses/LICENSE
xcbm-0.1.2.dist-info/METADATA
xcbm-0.1.2.dist-info/WHEEL
xcbm-0.1.2.dist-info/top_level.txt
xcbm-0.1.2.dist-info/RECORD
