Metadata-Version: 2.4
Name: xcbm
Version: 0.1.2
Summary: xcbm - A Python module to benchmark XC functional using PySCF and Psi4 packages on MGCDB84 dataset
Requires-Python: >=3.9
License-File: LICENSE
Dynamic: license-file
